fastapi_tortoise_pagination/Params.py
fastapi_tortoise_pagination/__init__.py
fastapi_tortoise_pagination/pagination.py
fastapi_tortoise_pagination/response_model.py
fastapi_tortoise_pagination-0.1.3.dist-info/LICENSE
fastapi_tortoise_pagination-0.1.3.dist-info/METADATA
fastapi_tortoise_pagination-0.1.3.dist-info/WHEEL
fastapi_tortoise_pagination-0.1.3.dist-info/top_level.txt
fastapi_tortoise_pagination-0.1.3.dist-info/RECORD
