Metadata-Version: 2.1
Name: fastapi-tortoise-pagination
Version: 0.1.3
Summary: A paginator based on fastapi and tortoise-orm
Home-page: https://github.com/NotBeBarnon/fastapi-tortoise-pagination
Author: fengzhixiong
Author-email: 1775894560@qq.com
Classifier: Programming Language :: Python :: 3
Classifier: License :: OSI Approved :: MIT License
Classifier: Operating System :: OS Independent
License-File: LICENSE
